ezweld/__init__.py
ezweld/weldgroup.py
ezweld-0.2.1.dist-info/METADATA
ezweld-0.2.1.dist-info/WHEEL
ezweld-0.2.1.dist-info/licenses/LICENSE
ezweld-0.2.1.dist-info/RECORD
