Metadata-Version: 2.4
Name: ezweld
Version: 0.2.1
Summary: ezweld - weld stress calculations in python
Project-URL: Homepage, https://github.com/wcfrobert/ezweld
Project-URL: Bug Tracker, https://github.com/wcfrobert/ezweld/issues
Author-email: wcfrobert <temprobertdev@gmail.com>
License-File: LICENSE
Keywords: connections,steel,structural engineering,weld stress,welding
Classifier: License :: OSI Approved :: MIT License
Classifier: Operating System :: OS Independent
Classifier: Programming Language :: Python :: 3
Requires-Python: >=3.7
Requires-Dist: matplotlib>=3.0
Requires-Dist: numpy>=2.0
Requires-Dist: pandas>=2.0
Requires-Dist: plotly>=5.0
